[{"county":"Adams","year":"1990","population":13603},{"county":"Adams","year":"1991","population":13823},{"county":"Adams","year":"1992","population":14063},{"county":"Adams","year":"1993","population":14335},{"county":"Adams","year":"1994","population":14679},{"county":"Adams","year":"1995","population":15030},{"county":"Adams","year":"1996","population":15323},{"county":"Adams","year":"1997","population":15698},{"county":"Adams","year":"1998","population":15879},{"county":"Adams","year":"1999","population":16151},{"county":"Adams","year":"2000","population":16428},{"county":"Adams","year":"2001","population":16699},{"county":"Adams","year":"2002","population":16911},{"county":"Adams","year":"2003","population":17081},{"county":"Adams","year":"2004","population":17489},{"county":"Adams","year":"2005","population":17643},{"county":"Adams","year":"2006","population":17690},{"county":"Adams","year":"2007","population":17959},{"county":"Adams","year":"2008","population":18214},{"county":"Adams","year":"2009","population":18421},{"county":"Adams","year":"2010","population":18728},{"county":"Adams","year":"2011","population":18950},{"county":"Adams","year":"2012","population":19050},{"county":"Adams","year":"2013","population":19200},{"county":"Asotin","year":"1990","population":17605},{"county":"Asotin","year":"1991","population":17677},{"county":"Asotin","year":"1992","population":17866},{"county":"Asotin","year":"1993","population":18124},{"county":"Asotin","year":"1994","population":18666},{"county":"Asotin","year":"1995","population":18937},{"county":"Asotin","year":"1996","population":19622},{"county":"Asotin","year":"1997","population":19943},{"county":"Asotin","year":"1998","population":20202},{"county":"Asotin","year":"1999","population":20442},{"county":"Asotin","year":"2000","population":20551},{"county":"Asotin","year":"2001","population":20650},{"county":"Asotin","year":"2002","population":20652},{"county":"Asotin","year":"2003","population":20709},{"county":"Asotin","year":"2004","population":20779},{"county":"Asotin","year":"2005","population":20939},{"county":"Asotin","year":"2006","population":21176},{"county":"Asotin","year":"2007","population":21413},{"county":"Asotin","year":"2008","population":21522},{"county":"Asotin","year":"2009","population":21593},{"county":"Asotin","year":"2010","population":21623},{"county":"Asotin","year":"2011","population":21650},{"county":"Asotin","year":"2012","population":21700},{"county":"Asotin","year":"2013","population":21800},{"county":"Benton","year":"1990","population":112560},{"county":"Benton","year":"1991","population":114439},{"county":"Benton","year":"1992","population":116503},{"county":"Benton","year":"1993","population":119374},{"county":"Benton","year":"1994","population":123457},{"county":"Benton","year":"1995","population":128359},{"county":"Benton","year":"1996","population":132590},{"county":"Benton","year":"1997","population":135620},{"county":"Benton","year":"1998","population":137717},{"county":"Benton","year":"1999","population":139498},{"county":"Benton","year":"2000","population":142475},{"county":"Benton","year":"2001","population":145267},{"county":"Benton","year":"2002","population":148290},{"county":"Benton","year":"2003","population":151933},{"county":"Benton","year":"2004","population":155874},{"county":"Benton","year":"2005","population":159286},{"county":"Benton","year":"2006","population":162255},{"county":"Benton","year":"2007","population":165096},{"county":"Benton","year":"2008","population":167598},{"county":"Benton","year":"2009","population":171402},{"county":"Benton","year":"2010","population":175177},{"county":"Benton","year":"2011","population":177900},{"county":"Benton","year":"2012","population":180000},{"county":"Benton","year":"2013","population":183400},{"county":"Chelan","year":"1990","population":52250},{"county":"Chelan","year":"1991","population":53436},{"county":"Chelan","year":"1992","population":54965},{"county":"Chelan","year":"1993","population":56423},{"county":"Chelan","year":"1994","population":58319},{"county":"Chelan","year":"1995","population":60079},{"county":"Chelan","year":"1996","population":61240},{"county":"Chelan","year":"1997","population":62895},{"county":"Chelan","year":"1998","population":64199},{"county":"Chelan","year":"1999","population":65575},{"county":"Chelan","year":"2000","population":66616},{"county":"Chelan","year":"2001","population":66896},{"county":"Chelan","year":"2002","population":67400},{"county":"Chelan","year":"2003","population":67507},{"county":"Chelan","year":"2004","population":68013},{"county":"Chelan","year":"2005","population":68963},{"county":"Chelan","year":"2006","population":69895},{"county":"Chelan","year":"2007","population":70773},{"county":"Chelan","year":"2008","population":71799},{"county":"Chelan","year":"2009","population":72185},{"county":"Chelan","year":"2010","population":72453},{"county":"Chelan","year":"2011","population":72700},{"county":"Chelan","year":"2012","population":73200},{"county":"Chelan","year":"2013","population":73600},{"county":"Clallam","year":"1990","population":56210},{"county":"Clallam","year":"1991","population":57626},{"county":"Clallam","year":"1992","population":58275},{"county":"Clallam","year":"1993","population":59155},{"county":"Clallam","year":"1994","population":59919},{"county":"Clallam","year":"1995","population":60548},{"county":"Clallam","year":"1996","population":61469},{"county":"Clallam","year":"1997","population":62037},{"county":"Clallam","year":"1998","population":62933},{"county":"Clallam","year":"1999","population":63425},{"county":"Clallam","year":"2000","population":64179},{"county":"Clallam","year":"2001","population":64717},{"county":"Clallam","year":"2002","population":65398},{"county":"Clallam","year":"2003","population":65928},{"county":"Clallam","year":"2004","population":66725},{"county":"Clallam","year":"2005","population":67672},{"county":"Clallam","year":"2006","population":68948},{"county":"Clallam","year":"2007","population":69847},{"county":"Clallam","year":"2008","population":70629},{"county":"Clallam","year":"2009","population":71027},{"county":"Clallam","year":"2010","population":71404},{"county":"Clallam","year":"2011","population":71600},{"county":"Clallam","year":"2012","population":72000},{"county":"Clallam","year":"2013","population":72350},{"county":"Clark","year":"1990","population":238053},{"county":"Clark","year":"1991","population":248417},{"county":"Clark","year":"1992","population":255915},{"county":"Clark","year":"1993","population":264548},{"county":"Clark","year":"1994","population":274423},{"county":"Clark","year":"1995","population":286804},{"county":"Clark","year":"1996","population":298364},{"county":"Clark","year":"1997","population":310512},{"county":"Clark","year":"1998","population":323892},{"county":"Clark","year":"1999","population":334641},{"county":"Clark","year":"2000","population":345238},{"county":"Clark","year":"2001","population":352715},{"county":"Clark","year":"2002","population":364855},{"county":"Clark","year":"2003","population":374091},{"county":"Clark","year":"2004","population":385370},{"county":"Clark","year":"2005","population":394600},{"county":"Clark","year":"2006","population":404737},{"county":"Clark","year":"2007","population":412692},{"county":"Clark","year":"2008","population":419091},{"county":"Clark","year":"2009","population":423775},{"county":"Clark","year":"2010","population":425363},{"county":"Clark","year":"2011","population":428000},{"county":"Clark","year":"2012","population":431250},{"county":"Clark","year":"2013","population":435500},{"county":"Columbia","year":"1990","population":4024},{"county":"Columbia","year":"1991","population":4044},{"county":"Columbia","year":"1992","population":4041},{"county":"Columbia","year":"1993","population":4047},{"county":"Columbia","year":"1994","population":4053},{"county":"Columbia","year":"1995","population":4051},{"county":"Columbia","year":"1996","population":4051},{"county":"Columbia","year":"1997","population":4056},{"county":"Columbia","year":"1998","population":4058},{"county":"Columbia","year":"1999","population":4062},{"county":"Columbia","year":"2000","population":4064},{"county":"Columbia","year":"2001","population":4114},{"county":"Columbia","year":"2002","population":4115},{"county":"Columbia","year":"2003","population":4111},{"county":"Columbia","year":"2004","population":4122},{"county":"Columbia","year":"2005","population":4135},{"county":"Columbia","year":"2006","population":4128},{"county":"Columbia","year":"2007","population":4095},{"county":"Columbia","year":"2008","population":4099},{"county":"Columbia","year":"2009","population":4097},{"county":"Columbia","year":"2010","population":4078},{"county":"Columbia","year":"2011","population":4100},{"county":"Columbia","year":"2012","population":4100},{"county":"Columbia","year":"2013","population":4100},{"county":"Cowlitz","year":"1990","population":82119},{"county":"Cowlitz","year":"1991","population":82862},{"county":"Cowlitz","year":"1992","population":83802},{"county":"Cowlitz","year":"1993","population":84813},{"county":"Cowlitz","year":"1994","population":85921},{"county":"Cowlitz","year":"1995","population":87232},{"county":"Cowlitz","year":"1996","population":88531},{"county":"Cowlitz","year":"1997","population":89568},{"county":"Cowlitz","year":"1998","population":90600},{"county":"Cowlitz","year":"1999","population":91744},{"county":"Cowlitz","year":"2000","population":92948},{"county":"Cowlitz","year":"2001","population":94081},{"county":"Cowlitz","year":"2002","population":94854},{"county":"Cowlitz","year":"2003","population":95849},{"county":"Cowlitz","year":"2004","population":96593},{"county":"Cowlitz","year":"2005","population":97673},{"county":"Cowlitz","year":"2006","population":99095},{"county":"Cowlitz","year":"2007","population":100377},{"county":"Cowlitz","year":"2008","population":101542},{"county":"Cowlitz","year":"2009","population":102175},{"county":"Cowlitz","year":"2010","population":102410},{"county":"Cowlitz","year":"2011","population":102700},{"county":"Cowlitz","year":"2012","population":103050},{"county":"Cowlitz","year":"2013","population":103300},{"county":"Douglas","year":"1990","population":26195},{"county":"Douglas","year":"1991","population":27648},{"county":"Douglas","year":"1992","population":27423},{"county":"Douglas","year":"1993","population":28143},{"county":"Douglas","year":"1994","population":28692},{"county":"Douglas","year":"1995","population":29312},{"county":"Douglas","year":"1996","population":29967},{"county":"Douglas","year":"1997","population":30548},{"county":"Douglas","year":"1998","population":31427},{"county":"Douglas","year":"1999","population":32035},{"county":"Douglas","year":"2000","population":32603},{"county":"Douglas","year":"2001","population":32817},{"county":"Douglas","year":"2002","population":32871},{"county":"Douglas","year":"2003","population":33545},{"county":"Douglas","year":"2004","population":33944},{"county":"Douglas","year":"2005","population":34466},{"county":"Douglas","year":"2006","population":35505},{"county":"Douglas","year":"2007","population":36340},{"county":"Douglas","year":"2008","population":37238},{"county":"Douglas","year":"2009","population":38036},{"county":"Douglas","year":"2010","population":38431},{"county":"Douglas","year":"2011","population":38650},{"county":"Douglas","year":"2012","population":38900},{"county":"Douglas","year":"2013","population":39280},{"county":"Ferry","year":"1990","population":6295},{"county":"Ferry","year":"1991","population":6366},{"county":"Ferry","year":"1992","population":6465},{"county":"Ferry","year":"1993","population":6561},{"county":"Ferry","year":"1994","population":6648},{"county":"Ferry","year":"1995","population":6812},{"county":"Ferry","year":"1996","population":6950},{"county":"Ferry","year":"1997","population":7058},{"county":"Ferry","year":"1998","population":7135},{"county":"Ferry","year":"1999","population":7184},{"county":"Ferry","year":"2000","population":7260},{"county":"Ferry","year":"2001","population":7340},{"county":"Ferry","year":"2002","population":7378},{"county":"Ferry","year":"2003","population":7397},{"county":"Ferry","year":"2004","population":7367},{"county":"Ferry","year":"2005","population":7405},{"county":"Ferry","year":"2006","population":7462},{"county":"Ferry","year":"2007","population":7484},{"county":"Ferry","year":"2008","population":7529},{"county":"Ferry","year":"2009","population":7563},{"county":"Ferry","year":"2010","population":7551},{"county":"Ferry","year":"2011","population":7600},{"county":"Ferry","year":"2012","population":7650},{"county":"Ferry","year":"2013","population":7650},{"county":"Franklin","year":"1990","population":37473},{"county":"Franklin","year":"1991","population":38522},{"county":"Franklin","year":"1992","population":39077},{"county":"Franklin","year":"1993","population":40092},{"county":"Franklin","year":"1994","population":41280},{"county":"Franklin","year":"1995","population":42516},{"county":"Franklin","year":"1996","population":43694},{"county":"Franklin","year":"1997","population":45180},{"county":"Franklin","year":"1998","population":46465},{"county":"Franklin","year":"1999","population":47900},{"county":"Franklin","year":"2000","population":49347},{"county":"Franklin","year":"2001","population":50473},{"county":"Franklin","year":"2002","population":52286},{"county":"Franklin","year":"2003","population":54907},{"county":"Franklin","year":"2004","population":58576},{"county":"Franklin","year":"2005","population":62572},{"county":"Franklin","year":"2006","population":66371},{"county":"Franklin","year":"2007","population":69582},{"county":"Franklin","year":"2008","population":72230},{"county":"Franklin","year":"2009","population":75111},{"county":"Franklin","year":"2010","population":78163},{"county":"Franklin","year":"2011","population":80500},{"county":"Franklin","year":"2012","population":82500},{"county":"Franklin","year":"2013","population":84800},{"county":"Garfield","year":"1990","population":2248},{"county":"Garfield","year":"1991","population":2259},{"county":"Garfield","year":"1992","population":2272},{"county":"Garfield","year":"1993","population":2268},{"county":"Garfield","year":"1994","population":2310},{"county":"Garfield","year":"1995","population":2322},{"county":"Garfield","year":"1996","population":2344},{"county":"Garfield","year":"1997","population":2354},{"county":"Garfield","year":"1998","population":2360},{"county":"Garfield","year":"1999","population":2372},{"county":"Garfield","year":"2000","population":2397},{"county":"Garfield","year":"2001","population":2382},{"county":"Garfield","year":"2002","population":2365},{"county":"Garfield","year":"2003","population":2348},{"county":"Garfield","year":"2004","population":2325},{"county":"Garfield","year":"2005","population":2315},{"county":"Garfield","year":"2006","population":2306},{"county":"Garfield","year":"2007","population":2287},{"county":"Garfield","year":"2008","population":2278},{"county":"Garfield","year":"2009","population":2272},{"county":"Garfield","year":"2010","population":2266},{"county":"Garfield","year":"2011","population":2250},{"county":"Garfield","year":"2012","population":2250},{"county":"Garfield","year":"2013","population":2250},{"county":"Grant","year":"1990","population":54798},{"county":"Grant","year":"1991","population":56008},{"county":"Grant","year":"1992","population":57596},{"county":"Grant","year":"1993","population":59444},{"county":"Grant","year":"1994","population":61638},{"county":"Grant","year":"1995","population":64099},{"county":"Grant","year":"1996","population":66484},{"county":"Grant","year":"1997","population":68359},{"county":"Grant","year":"1998","population":70578},{"county":"Grant","year":"1999","population":72718},{"county":"Grant","year":"2000","population":74698},{"county":"Grant","year":"2001","population":75899},{"county":"Grant","year":"2002","population":76942},{"county":"Grant","year":"2003","population":77493},{"county":"Grant","year":"2004","population":78979},{"county":"Grant","year":"2005","population":80121},{"county":"Grant","year":"2006","population":81792},{"county":"Grant","year":"2007","population":83729},{"county":"Grant","year":"2008","population":85983},{"county":"Grant","year":"2009","population":87721},{"county":"Grant","year":"2010","population":89120},{"county":"Grant","year":"2011","population":90100},{"county":"Grant","year":"2012","population":91000},{"county":"Grant","year":"2013","population":91800},{"county":"Grays Harbor","year":"1990","population":64175},{"county":"Grays Harbor","year":"1991","population":64309},{"county":"Grays Harbor","year":"1992","population":64636},{"county":"Grays Harbor","year":"1993","population":64930},{"county":"Grays Harbor","year":"1994","population":65441},{"county":"Grays Harbor","year":"1995","population":65820},{"county":"Grays Harbor","year":"1996","population":66172},{"county":"Grays Harbor","year":"1997","population":66553},{"county":"Grays Harbor","year":"1998","population":66568},{"county":"Grays Harbor","year":"1999","population":66766},{"county":"Grays Harbor","year":"2000","population":67194},{"county":"Grays Harbor","year":"2001","population":68709},{"county":"Grays Harbor","year":"2002","population":69229},{"county":"Grays Harbor","year":"2003","population":69445},{"county":"Grays Harbor","year":"2004","population":70069},{"county":"Grays Harbor","year":"2005","population":70812},{"county":"Grays Harbor","year":"2006","population":71582},{"county":"Grays Harbor","year":"2007","population":72038},{"county":"Grays Harbor","year":"2008","population":72295},{"county":"Grays Harbor","year":"2009","population":72569},{"county":"Grays Harbor","year":"2010","population":72797},{"county":"Grays Harbor","year":"2011","population":72900},{"county":"Grays Harbor","year":"2012","population":73150},{"county":"Grays Harbor","year":"2013","population":73200},{"county":"Island","year":"1990","population":60195},{"county":"Island","year":"1991","population":62176},{"county":"Island","year":"1992","population":63289},{"county":"Island","year":"1993","population":64303},{"county":"Island","year":"1994","population":65139},{"county":"Island","year":"1995","population":66378},{"county":"Island","year":"1996","population":67308},{"county":"Island","year":"1997","population":68536},{"county":"Island","year":"1998","population":69609},{"county":"Island","year":"1999","population":70629},{"county":"Island","year":"2000","population":71558},{"county":"Island","year":"2001","population":72062},{"county":"Island","year":"2002","population":73151},{"county":"Island","year":"2003","population":73630},{"county":"Island","year":"2004","population":74549},{"county":"Island","year":"2005","population":75951},{"county":"Island","year":"2006","population":77189},{"county":"Island","year":"2007","population":78225},{"county":"Island","year":"2008","population":78544},{"county":"Island","year":"2009","population":78737},{"county":"Island","year":"2010","population":78506},{"county":"Island","year":"2011","population":78800},{"county":"Island","year":"2012","population":79350},{"county":"Island","year":"2013","population":79700},{"county":"Jefferson","year":"1990","population":20406},{"county":"Jefferson","year":"1991","population":21144},{"county":"Jefferson","year":"1992","population":21940},{"county":"Jefferson","year":"1993","population":22641},{"county":"Jefferson","year":"1994","population":23313},{"county":"Jefferson","year":"1995","population":23950},{"county":"Jefferson","year":"1996","population":24412},{"county":"Jefferson","year":"1997","population":24925},{"county":"Jefferson","year":"1998","population":25322},{"county":"Jefferson","year":"1999","population":25865},{"county":"Jefferson","year":"2000","population":26299},{"county":"Jefferson","year":"2001","population":26665},{"county":"Jefferson","year":"2002","population":27143},{"county":"Jefferson","year":"2003","population":27343},{"county":"Jefferson","year":"2004","population":27738},{"county":"Jefferson","year":"2005","population":28356},{"county":"Jefferson","year":"2006","population":28847},{"county":"Jefferson","year":"2007","population":29244},{"county":"Jefferson","year":"2008","population":29634},{"county":"Jefferson","year":"2009","population":29773},{"county":"Jefferson","year":"2010","population":29872},{"county":"Jefferson","year":"2011","population":30050},{"county":"Jefferson","year":"2012","population":30175},{"county":"Jefferson","year":"2013","population":30275},{"county":"King","year":"1990","population":1507305},{"county":"King","year":"1991","population":1549991},{"county":"King","year":"1992","population":1570997},{"county":"King","year":"1993","population":1590603},{"county":"King","year":"1994","population":1609529},{"county":"King","year":"1995","population":1625241},{"county":"King","year":"1996","population":1640249},{"county":"King","year":"1997","population":1659106},{"county":"King","year":"1998","population":1686266},{"county":"King","year":"1999","population":1712122},{"county":"King","year":"2000","population":1737046},{"county":"King","year":"2001","population":1755487},{"county":"King","year":"2002","population":1777514},{"county":"King","year":"2003","population":1788082},{"county":"King","year":"2004","population":1800783},{"county":"King","year":"2005","population":1814999},{"county":"King","year":"2006","population":1845209},{"county":"King","year":"2007","population":1871098},{"county":"King","year":"2008","population":1891125},{"county":"King","year":"2009","population":1909205},{"county":"King","year":"2010","population":1931249},{"county":"King","year":"2011","population":1942600},{"county":"King","year":"2012","population":1957000},{"county":"King","year":"2013","population":1981900},{"county":"Kitsap","year":"1990","population":189731},{"county":"Kitsap","year":"1991","population":196926},{"county":"Kitsap","year":"1992","population":202113},{"county":"Kitsap","year":"1993","population":207976},{"county":"Kitsap","year":"1994","population":212429},{"county":"Kitsap","year":"1995","population":218308},{"county":"Kitsap","year":"1996","population":221849},{"county":"Kitsap","year":"1997","population":225251},{"county":"Kitsap","year":"1998","population":227179},{"county":"Kitsap","year":"1999","population":229569},{"county":"Kitsap","year":"2000","population":231969},{"county":"Kitsap","year":"2001","population":233918},{"county":"Kitsap","year":"2002","population":236656},{"county":"Kitsap","year":"2003","population":239443},{"county":"Kitsap","year":"2004","population":240777},{"county":"Kitsap","year":"2005","population":239819},{"county":"Kitsap","year":"2006","population":244049},{"county":"Kitsap","year":"2007","population":247476},{"county":"Kitsap","year":"2008","population":249905},{"county":"Kitsap","year":"2009","population":251249},{"county":"Kitsap","year":"2010","population":251133},{"county":"Kitsap","year":"2011","population":253900},{"county":"Kitsap","year":"2012","population":254500},{"county":"Kitsap","year":"2013","population":254000},{"county":"Kittitas","year":"1990","population":26725},{"county":"Kittitas","year":"1991","population":27203},{"county":"Kittitas","year":"1992","population":27684},{"county":"Kittitas","year":"1993","population":28295},{"county":"Kittitas","year":"1994","population":28938},{"county":"Kittitas","year":"1995","population":29791},{"county":"Kittitas","year":"1996","population":30372},{"county":"Kittitas","year":"1997","population":30989},{"county":"Kittitas","year":"1998","population":31845},{"county":"Kittitas","year":"1999","population":32916},{"county":"Kittitas","year":"2000","population":33362},{"county":"Kittitas","year":"2001","population":33936},{"county":"Kittitas","year":"2002","population":34507},{"county":"Kittitas","year":"2003","population":35474},{"county":"Kittitas","year":"2004","population":36773},{"county":"Kittitas","year":"2005","population":37660},{"county":"Kittitas","year":"2006","population":38175},{"county":"Kittitas","year":"2007","population":39134},{"county":"Kittitas","year":"2008","population":40142},{"county":"Kittitas","year":"2009","population":40710},{"county":"Kittitas","year":"2010","population":40915},{"county":"Kittitas","year":"2011","population":41300},{"county":"Kittitas","year":"2012","population":41500},{"county":"Kittitas","year":"2013","population":41900},{"county":"Klickitat","year":"1990","population":16616},{"county":"Klickitat","year":"1991","population":16770},{"county":"Klickitat","year":"1992","population":16858},{"county":"Klickitat","year":"1993","population":17067},{"county":"Klickitat","year":"1994","population":17295},{"county":"Klickitat","year":"1995","population":17603},{"county":"Klickitat","year":"1996","population":17926},{"county":"Klickitat","year":"1997","population":18244},{"county":"Klickitat","year":"1998","population":18573},{"county":"Klickitat","year":"1999","population":18894},{"county":"Klickitat","year":"2000","population":19161},{"county":"Klickitat","year":"2001","population":19284},{"county":"Klickitat","year":"2002","population":19364},{"county":"Klickitat","year":"2003","population":19463},{"county":"Klickitat","year":"2004","population":19652},{"county":"Klickitat","year":"2005","population":19753},{"county":"Klickitat","year":"2006","population":19979},{"county":"Klickitat","year":"2007","population":20108},{"county":"Klickitat","year":"2008","population":20216},{"county":"Klickitat","year":"2009","population":20256},{"county":"Klickitat","year":"2010","population":20318},{"county":"Klickitat","year":"2011","population":20500},{"county":"Klickitat","year":"2012","population":20600},{"county":"Klickitat","year":"2013","population":20700},{"county":"Lewis","year":"1990","population":59358},{"county":"Lewis","year":"1991","population":59975},{"county":"Lewis","year":"1992","population":60662},{"county":"Lewis","year":"1993","population":61523},{"county":"Lewis","year":"1994","population":62456},{"county":"Lewis","year":"1995","population":63835},{"county":"Lewis","year":"1996","population":65043},{"county":"Lewis","year":"1997","population":66182},{"county":"Lewis","year":"1998","population":67119},{"county":"Lewis","year":"1999","population":67830},{"county":"Lewis","year":"2000","population":68600},{"county":"Lewis","year":"2001","population":69372},{"county":"Lewis","year":"2002","population":70098},{"county":"Lewis","year":"2003","population":70395},{"county":"Lewis","year":"2004","population":71063},{"county":"Lewis","year":"2005","population":71771},{"county":"Lewis","year":"2006","population":73041},{"county":"Lewis","year":"2007","population":74026},{"county":"Lewis","year":"2008","population":74843},{"county":"Lewis","year":"2009","population":75305},{"county":"Lewis","year":"2010","population":75455},{"county":"Lewis","year":"2011","population":76000},{"county":"Lewis","year":"2012","population":76300},{"county":"Lewis","year":"2013","population":76200},{"county":"Lincoln","year":"1990","population":8864},{"county":"Lincoln","year":"1991","population":8939},{"county":"Lincoln","year":"1992","population":8973},{"county":"Lincoln","year":"1993","population":9036},{"county":"Lincoln","year":"1994","population":9181},{"county":"Lincoln","year":"1995","population":9330},{"county":"Lincoln","year":"1996","population":9471},{"county":"Lincoln","year":"1997","population":9623},{"county":"Lincoln","year":"1998","population":9838},{"county":"Lincoln","year":"1999","population":10020},{"county":"Lincoln","year":"2000","population":10184},{"county":"Lincoln","year":"2001","population":10319},{"county":"Lincoln","year":"2002","population":10277},{"county":"Lincoln","year":"2003","population":10155},{"county":"Lincoln","year":"2004","population":10305},{"county":"Lincoln","year":"2005","population":10367},{"county":"Lincoln","year":"2006","population":10435},{"county":"Lincoln","year":"2007","population":10536},{"county":"Lincoln","year":"2008","population":10629},{"county":"Lincoln","year":"2009","population":10624},{"county":"Lincoln","year":"2010","population":10570},{"county":"Lincoln","year":"2011","population":10600},{"county":"Lincoln","year":"2012","population":10675},{"county":"Lincoln","year":"2013","population":10675},{"county":"Mason","year":"1990","population":38341},{"county":"Mason","year":"1991","population":39473},{"county":"Mason","year":"1992","population":40524},{"county":"Mason","year":"1993","population":41693},{"county":"Mason","year":"1994","population":42918},{"county":"Mason","year":"1995","population":44128},{"county":"Mason","year":"1996","population":45261},{"county":"Mason","year":"1997","population":46350},{"county":"Mason","year":"1998","population":47421},{"county":"Mason","year":"1999","population":48410},{"county":"Mason","year":"2000","population":49405},{"county":"Mason","year":"2001","population":49979},{"county":"Mason","year":"2002","population":50981},{"county":"Mason","year":"2003","population":51963},{"county":"Mason","year":"2004","population":53233},{"county":"Mason","year":"2005","population":54739},{"county":"Mason","year":"2006","population":56214},{"county":"Mason","year":"2007","population":58066},{"county":"Mason","year":"2008","population":59536},{"county":"Mason","year":"2009","population":60237},{"county":"Mason","year":"2010","population":60699},{"county":"Mason","year":"2011","population":61100},{"county":"Mason","year":"2012","population":61450},{"county":"Mason","year":"2013","population":61800},{"county":"Okanogan","year":"1990","population":33350},{"county":"Okanogan","year":"1991","population":33834},{"county":"Okanogan","year":"1992","population":34388},{"county":"Okanogan","year":"1993","population":35004},{"county":"Okanogan","year":"1994","population":35709},{"county":"Okanogan","year":"1995","population":36702},{"county":"Okanogan","year":"1996","population":37501},{"county":"Okanogan","year":"1997","population":38236},{"county":"Okanogan","year":"1998","population":38629},{"county":"Okanogan","year":"1999","population":39066},{"county":"Okanogan","year":"2000","population":39564},{"county":"Okanogan","year":"2001","population":39828},{"county":"Okanogan","year":"2002","population":39992},{"county":"Okanogan","year":"2003","population":39994},{"county":"Okanogan","year":"2004","population":40160},{"county":"Okanogan","year":"2005","population":40267},{"county":"Okanogan","year":"2006","population":40656},{"county":"Okanogan","year":"2007","population":40428},{"county":"Okanogan","year":"2008","population":40589},{"county":"Okanogan","year":"2009","population":40968},{"county":"Okanogan","year":"2010","population":41120},{"county":"Okanogan","year":"2011","population":41200},{"county":"Okanogan","year":"2012","population":41425},{"county":"Okanogan","year":"2013","population":41500},{"county":"Pacific","year":"1990","population":18882},{"county":"Pacific","year":"1991","population":19024},{"county":"Pacific","year":"1992","population":19221},{"county":"Pacific","year":"1993","population":19449},{"county":"Pacific","year":"1994","population":19700},{"county":"Pacific","year":"1995","population":19990},{"county":"Pacific","year":"1996","population":20240},{"county":"Pacific","year":"1997","population":20420},{"county":"Pacific","year":"1998","population":20655},{"county":"Pacific","year":"1999","population":20823},{"county":"Pacific","year":"2000","population":20984},{"county":"Pacific","year":"2001","population":20950},{"county":"Pacific","year":"2002","population":20873},{"county":"Pacific","year":"2003","population":20661},{"county":"Pacific","year":"2004","population":20662},{"county":"Pacific","year":"2005","population":20675},{"county":"Pacific","year":"2006","population":20905},{"county":"Pacific","year":"2007","population":20790},{"county":"Pacific","year":"2008","population":20751},{"county":"Pacific","year":"2009","population":20888},{"county":"Pacific","year":"2010","population":20920},{"county":"Pacific","year":"2011","population":20900},{"county":"Pacific","year":"2012","population":20970},{"county":"Pacific","year":"2013","population":21000},{"county":"Pend Oreille","year":"1990","population":8915},{"county":"Pend Oreille","year":"1991","population":9154},{"county":"Pend Oreille","year":"1992","population":9353},{"county":"Pend Oreille","year":"1993","population":9627},{"county":"Pend Oreille","year":"1994","population":9918},{"county":"Pend Oreille","year":"1995","population":10267},{"county":"Pend Oreille","year":"1996","population":10579},{"county":"Pend Oreille","year":"1997","population":10857},{"county":"Pend Oreille","year":"1998","population":11146},{"county":"Pend Oreille","year":"1999","population":11429},{"county":"Pend Oreille","year":"2000","population":11732},{"county":"Pend Oreille","year":"2001","population":11986},{"county":"Pend Oreille","year":"2002","population":11998},{"county":"Pend Oreille","year":"2003","population":12091},{"county":"Pend Oreille","year":"2004","population":12174},{"county":"Pend Oreille","year":"2005","population":12356},{"county":"Pend Oreille","year":"2006","population":12503},{"county":"Pend Oreille","year":"2007","population":12659},{"county":"Pend Oreille","year":"2008","population":12855},{"county":"Pend Oreille","year":"2009","population":12836},{"county":"Pend Oreille","year":"2010","population":13001},{"county":"Pend Oreille","year":"2011","population":13000},{"county":"Pend Oreille","year":"2012","population":13100},{"county":"Pend Oreille","year":"2013","population":13150},{"county":"Pierce","year":"1990","population":586203},{"county":"Pierce","year":"1991","population":598065},{"county":"Pierce","year":"1992","population":610619},{"county":"Pierce","year":"1993","population":623697},{"county":"Pierce","year":"1994","population":636802},{"county":"Pierce","year":"1995","population":649284},{"county":"Pierce","year":"1996","population":653212},{"county":"Pierce","year":"1997","population":664070},{"county":"Pierce","year":"1998","population":675651},{"county":"Pierce","year":"1999","population":688884},{"county":"Pierce","year":"2000","population":700818},{"county":"Pierce","year":"2001","population":709288},{"county":"Pierce","year":"2002","population":721124},{"county":"Pierce","year":"2003","population":731969},{"county":"Pierce","year":"2004","population":743701},{"county":"Pierce","year":"2005","population":756919},{"county":"Pierce","year":"2006","population":774050},{"county":"Pierce","year":"2007","population":786911},{"county":"Pierce","year":"2008","population":794330},{"county":"Pierce","year":"2009","population":796900},{"county":"Pierce","year":"2010","population":795225},{"county":"Pierce","year":"2011","population":802150},{"county":"Pierce","year":"2012","population":808200},{"county":"Pierce","year":"2013","population":814500},{"county":"San Juan","year":"1990","population":10035},{"county":"San Juan","year":"1991","population":10783},{"county":"San Juan","year":"1992","population":11379},{"county":"San Juan","year":"1993","population":12049},{"county":"San Juan","year":"1994","population":12409},{"county":"San Juan","year":"1995","population":12747},{"county":"San Juan","year":"1996","population":12833},{"county":"San Juan","year":"1997","population":12949},{"county":"San Juan","year":"1998","population":13042},{"county":"San Juan","year":"1999","population":13506},{"county":"San Juan","year":"2000","population":14077},{"county":"San Juan","year":"2001","population":14402},{"county":"San Juan","year":"2002","population":14664},{"county":"San Juan","year":"2003","population":14772},{"county":"San Juan","year":"2004","population":14935},{"county":"San Juan","year":"2005","population":15180},{"county":"San Juan","year":"2006","population":15379},{"county":"San Juan","year":"2007","population":15483},{"county":"San Juan","year":"2008","population":15634},{"county":"San Juan","year":"2009","population":15738},{"county":"San Juan","year":"2010","population":15769},{"county":"San Juan","year":"2011","population":15900},{"county":"San Juan","year":"2012","population":15925},{"county":"San Juan","year":"2013","population":16000},{"county":"Skagit","year":"1990","population":79545},{"county":"Skagit","year":"1991","population":82803},{"county":"Skagit","year":"1992","population":85023},{"county":"Skagit","year":"1993","population":87550},{"county":"Skagit","year":"1994","population":90120},{"county":"Skagit","year":"1995","population":92627},{"county":"Skagit","year":"1996","population":94781},{"county":"Skagit","year":"1997","population":96950},{"county":"Skagit","year":"1998","population":98750},{"county":"Skagit","year":"1999","population":100421},{"county":"Skagit","year":"2000","population":102979},{"county":"Skagit","year":"2001","population":104246},{"county":"Skagit","year":"2002","population":105861},{"county":"Skagit","year":"2003","population":106647},{"county":"Skagit","year":"2004","population":108494},{"county":"Skagit","year":"2005","population":109977},{"county":"Skagit","year":"2006","population":112113},{"county":"Skagit","year":"2007","population":113890},{"county":"Skagit","year":"2008","population":115422},{"county":"Skagit","year":"2009","population":116612},{"county":"Skagit","year":"2010","population":116901},{"county":"Skagit","year":"2011","population":117400},{"county":"Skagit","year":"2012","population":117950},{"county":"Skagit","year":"2013","population":118600},{"county":"Skamania","year":"1990","population":8289},{"county":"Skamania","year":"1991","population":8532},{"county":"Skamania","year":"1992","population":8625},{"county":"Skamania","year":"1993","population":8736},{"county":"Skamania","year":"1994","population":8908},{"county":"Skamania","year":"1995","population":9057},{"county":"Skamania","year":"1996","population":9236},{"county":"Skamania","year":"1997","population":9402},{"county":"Skamania","year":"1998","population":9558},{"county":"Skamania","year":"1999","population":9744},{"county":"Skamania","year":"2000","population":9872},{"county":"Skamania","year":"2001","population":9941},{"county":"Skamania","year":"2002","population":10045},{"county":"Skamania","year":"2003","population":10117},{"county":"Skamania","year":"2004","population":10284},{"county":"Skamania","year":"2005","population":10515},{"county":"Skamania","year":"2006","population":10777},{"county":"Skamania","year":"2007","population":10892},{"county":"Skamania","year":"2008","population":10941},{"county":"Skamania","year":"2009","population":10995},{"county":"Skamania","year":"2010","population":11066},{"county":"Skamania","year":"2011","population":11150},{"county":"Skamania","year":"2012","population":11275},{"county":"Skamania","year":"2013","population":11300},{"county":"Snohomish","year":"1990","population":465628},{"county":"Snohomish","year":"1991","population":488075},{"county":"Snohomish","year":"1992","population":496461},{"county":"Snohomish","year":"1993","population":507336},{"county":"Snohomish","year":"1994","population":519960},{"county":"Snohomish","year":"1995","population":531704},{"county":"Snohomish","year":"1996","population":542738},{"county":"Snohomish","year":"1997","population":554585},{"county":"Snohomish","year":"1998","population":570896},{"county":"Snohomish","year":"1999","population":589266},{"county":"Snohomish","year":"2000","population":606024},{"county":"Snohomish","year":"2001","population":617864},{"county":"Snohomish","year":"2002","population":629287},{"county":"Snohomish","year":"2003","population":639942},{"county":"Snohomish","year":"2004","population":648778},{"county":"Snohomish","year":"2005","population":661346},{"county":"Snohomish","year":"2006","population":676126},{"county":"Snohomish","year":"2007","population":689314},{"county":"Snohomish","year":"2008","population":699330},{"county":"Snohomish","year":"2009","population":705894},{"county":"Snohomish","year":"2010","population":713335},{"county":"Snohomish","year":"2011","population":717000},{"county":"Snohomish","year":"2012","population":722900},{"county":"Snohomish","year":"2013","population":730500},{"county":"Spokane","year":"1990","population":361333},{"county":"Spokane","year":"1991","population":365887},{"county":"Spokane","year":"1992","population":371147},{"county":"Spokane","year":"1993","population":377020},{"county":"Spokane","year":"1994","population":384035},{"county":"Spokane","year":"1995","population":391318},{"county":"Spokane","year":"1996","population":397508},{"county":"Spokane","year":"1997","population":403954},{"county":"Spokane","year":"1998","population":408740},{"county":"Spokane","year":"1999","population":413665},{"county":"Spokane","year":"2000","population":417939},{"county":"Spokane","year":"2001","population":423127},{"county":"Spokane","year":"2002","population":428755},{"county":"Spokane","year":"2003","population":428889},{"county":"Spokane","year":"2004","population":431905},{"county":"Spokane","year":"2005","population":438249},{"county":"Spokane","year":"2006","population":446751},{"county":"Spokane","year":"2007","population":454034},{"county":"Spokane","year":"2008","population":460303},{"county":"Spokane","year":"2009","population":466426},{"county":"Spokane","year":"2010","population":471221},{"county":"Spokane","year":"2011","population":472650},{"county":"Spokane","year":"2012","population":475600},{"county":"Spokane","year":"2013","population":480000},{"county":"Stevens","year":"1990","population":30948},{"county":"Stevens","year":"1991","population":31617},{"county":"Stevens","year":"1992","population":32339},{"county":"Stevens","year":"1993","population":33250},{"county":"Stevens","year":"1994","population":34250},{"county":"Stevens","year":"1995","population":35523},{"county":"Stevens","year":"1996","population":36504},{"county":"Stevens","year":"1997","population":37405},{"county":"Stevens","year":"1998","population":38253},{"county":"Stevens","year":"1999","population":39122},{"county":"Stevens","year":"2000","population":40066},{"county":"Stevens","year":"2001","population":40331},{"county":"Stevens","year":"2002","population":40611},{"county":"Stevens","year":"2003","population":40960},{"county":"Stevens","year":"2004","population":41333},{"county":"Stevens","year":"2005","population":41792},{"county":"Stevens","year":"2006","population":42355},{"county":"Stevens","year":"2007","population":42759},{"county":"Stevens","year":"2008","population":43283},{"county":"Stevens","year":"2009","population":43510},{"county":"Stevens","year":"2010","population":43531},{"county":"Stevens","year":"2011","population":43600},{"county":"Stevens","year":"2012","population":43700},{"county":"Stevens","year":"2013","population":43800},{"county":"Thurston","year":"1990","population":161238},{"county":"Thurston","year":"1991","population":167663},{"county":"Thurston","year":"1992","population":172425},{"county":"Thurston","year":"1993","population":177058},{"county":"Thurston","year":"1994","population":181715},{"county":"Thurston","year":"1995","population":186419},{"county":"Thurston","year":"1996","population":190409},{"county":"Thurston","year":"1997","population":194440},{"county":"Thurston","year":"1998","population":198435},{"county":"Thurston","year":"1999","population":203167},{"county":"Thurston","year":"2000","population":207355},{"county":"Thurston","year":"2001","population":210102},{"county":"Thurston","year":"2002","population":214139},{"county":"Thurston","year":"2003","population":218264},{"county":"Thurston","year":"2004","population":223065},{"county":"Thurston","year":"2005","population":229286},{"county":"Thurston","year":"2006","population":234083},{"county":"Thurston","year":"2007","population":239570},{"county":"Thurston","year":"2008","population":244853},{"county":"Thurston","year":"2009","population":249336},{"county":"Thurston","year":"2010","population":252264},{"county":"Thurston","year":"2011","population":254100},{"county":"Thurston","year":"2012","population":256800},{"county":"Thurston","year":"2013","population":260100},{"county":"Wahkiakum","year":"1990","population":3327},{"county":"Wahkiakum","year":"1991","population":3347},{"county":"Wahkiakum","year":"1992","population":3358},{"county":"Wahkiakum","year":"1993","population":3420},{"county":"Wahkiakum","year":"1994","population":3482},{"county":"Wahkiakum","year":"1995","population":3546},{"county":"Wahkiakum","year":"1996","population":3615},{"county":"Wahkiakum","year":"1997","population":3656},{"county":"Wahkiakum","year":"1998","population":3693},{"county":"Wahkiakum","year":"1999","population":3758},{"county":"Wahkiakum","year":"2000","population":3824},{"county":"Wahkiakum","year":"2001","population":3831},{"county":"Wahkiakum","year":"2002","population":3825},{"county":"Wahkiakum","year":"2003","population":3833},{"county":"Wahkiakum","year":"2004","population":3826},{"county":"Wahkiakum","year":"2005","population":3867},{"county":"Wahkiakum","year":"2006","population":3912},{"county":"Wahkiakum","year":"2007","population":3963},{"county":"Wahkiakum","year":"2008","population":4005},{"county":"Wahkiakum","year":"2009","population":4003},{"county":"Wahkiakum","year":"2010","population":3978},{"county":"Wahkiakum","year":"2011","population":4000},{"county":"Wahkiakum","year":"2012","population":4025},{"county":"Wahkiakum","year":"2013","population":4020},{"county":"Walla Walla","year":"1990","population":48439},{"county":"Walla Walla","year":"1991","population":48817},{"county":"Walla Walla","year":"1992","population":49361},{"county":"Walla Walla","year":"1993","population":50015},{"county":"Walla Walla","year":"1994","population":50761},{"county":"Walla Walla","year":"1995","population":51461},{"county":"Walla Walla","year":"1996","population":52162},{"county":"Walla Walla","year":"1997","population":53029},{"county":"Walla Walla","year":"1998","population":53962},{"county":"Walla Walla","year":"1999","population":54496},{"county":"Walla Walla","year":"2000","population":55180},{"county":"Walla Walla","year":"2001","population":55102},{"county":"Walla Walla","year":"2002","population":55242},{"county":"Walla Walla","year":"2003","population":55560},{"county":"Walla Walla","year":"2004","population":56167},{"county":"Walla Walla","year":"2005","population":57005},{"county":"Walla Walla","year":"2006","population":57224},{"county":"Walla Walla","year":"2007","population":57754},{"county":"Walla Walla","year":"2008","population":58063},{"county":"Walla Walla","year":"2009","population":58561},{"county":"Walla Walla","year":"2010","population":58781},{"county":"Walla Walla","year":"2011","population":58800},{"county":"Walla Walla","year":"2012","population":59100},{"county":"Walla Walla","year":"2013","population":59500},{"county":"Whatcom","year":"1990","population":127780},{"county":"Whatcom","year":"1991","population":132669},{"county":"Whatcom","year":"1992","population":137791},{"county":"Whatcom","year":"1993","population":141270},{"county":"Whatcom","year":"1994","population":146056},{"county":"Whatcom","year":"1995","population":149942},{"county":"Whatcom","year":"1996","population":154122},{"county":"Whatcom","year":"1997","population":157071},{"county":"Whatcom","year":"1998","population":160667},{"county":"Whatcom","year":"1999","population":163774},{"county":"Whatcom","year":"2000","population":166826},{"county":"Whatcom","year":"2001","population":170980},{"county":"Whatcom","year":"2002","population":174238},{"county":"Whatcom","year":"2003","population":175984},{"county":"Whatcom","year":"2004","population":180245},{"county":"Whatcom","year":"2005","population":184965},{"county":"Whatcom","year":"2006","population":190088},{"county":"Whatcom","year":"2007","population":195298},{"county":"Whatcom","year":"2008","population":197675},{"county":"Whatcom","year":"2009","population":199736},{"county":"Whatcom","year":"2010","population":201140},{"county":"Whatcom","year":"2011","population":202100},{"county":"Whatcom","year":"2012","population":203500},{"county":"Whatcom","year":"2013","population":205800},{"county":"Whitman","year":"1990","population":38775},{"county":"Whitman","year":"1991","population":38560},{"county":"Whitman","year":"1992","population":38770},{"county":"Whitman","year":"1993","population":38909},{"county":"Whitman","year":"1994","population":39064},{"county":"Whitman","year":"1995","population":39451},{"county":"Whitman","year":"1996","population":39590},{"county":"Whitman","year":"1997","population":40154},{"county":"Whitman","year":"1998","population":40610},{"county":"Whitman","year":"1999","population":40842},{"county":"Whitman","year":"2000","population":40740},{"county":"Whitman","year":"2001","population":40342},{"county":"Whitman","year":"2002","population":40635},{"county":"Whitman","year":"2003","population":40954},{"county":"Whitman","year":"2004","population":41686},{"county":"Whitman","year":"2005","population":42498},{"county":"Whitman","year":"2006","population":42848},{"county":"Whitman","year":"2007","population":42793},{"county":"Whitman","year":"2008","population":44066},{"county":"Whitman","year":"2009","population":44005},{"county":"Whitman","year":"2010","population":44776},{"county":"Whitman","year":"2011","population":44800},{"county":"Whitman","year":"2012","population":45950},{"county":"Whitman","year":"2013","population":46000},{"county":"Yakima","year":"1990","population":188823},{"county":"Yakima","year":"1991","population":191490},{"county":"Yakima","year":"1992","population":194939},{"county":"Yakima","year":"1993","population":198225},{"county":"Yakima","year":"1994","population":202044},{"county":"Yakima","year":"1995","population":206046},{"county":"Yakima","year":"1996","population":209381},{"county":"Yakima","year":"1997","population":212375},{"county":"Yakima","year":"1998","population":215587},{"county":"Yakima","year":"1999","population":219483},{"county":"Yakima","year":"2000","population":222581},{"county":"Yakima","year":"2001","population":224229},{"county":"Yakima","year":"2002","population":224790},{"county":"Yakima","year":"2003","population":227956},{"county":"Yakima","year":"2004","population":230002},{"county":"Yakima","year":"2005","population":231902},{"county":"Yakima","year":"2006","population":234408},{"county":"Yakima","year":"2007","population":236923},{"county":"Yakima","year":"2008","population":239524},{"county":"Yakima","year":"2009","population":241708},{"county":"Yakima","year":"2010","population":243231},{"county":"Yakima","year":"2011","population":244700},{"county":"Yakima","year":"2012","population":246000},{"county":"Yakima","year":"2013","population":247250}]